{"http://purl.org/dc/elements/1.1/date": ["2020-01-01"], "http://rdfs.org/ns/void#inDataset": ["http://www.opengis.net/geoepsg_dataset"], "http://www.opengis.net/ont/crs/mass": ["0.04616"], "http://www.opengis.net/ont/crs/orbital_period": ["15.624"], "http://www.opengis.net/ont/crs/planet_status": ["http://www.opengis.net/ont/crs/Confirmed"], "http://www.opengis.net/ont/crs/radius": ["http://www.opengis.net/ont/crs/isbody/EPIC_249893012_c_radius"], "http://www.opengis.net/ont/crs/satelliteOf": ["http://www.opengis.net/ont/crs/isbody/EPIC_249893012"], "http://www.opengis.net/ont/crs/starDistance": ["324.7"], "http://www.w3.org/1999/02/22-rdf-syntax-ns#type": ["http://www.opengis.net/ont/crs/Planet"], "http://www.w3.org/2000/01/rdf-schema#label": ["EPIC 249893012 c"]}